pyevmosaddressconverter/__init__.py
pyevmosaddressconverter/enconder/__init__.py
pyevmosaddressconverter/enconder/bech32.py
tests/__init__.py
tests/test_converter.py
pyevmosaddressconverter-1.0.1.dist-info/LICENSE
pyevmosaddressconverter-1.0.1.dist-info/METADATA
pyevmosaddressconverter-1.0.1.dist-info/WHEEL
pyevmosaddressconverter-1.0.1.dist-info/top_level.txt
pyevmosaddressconverter-1.0.1.dist-info/RECORD
