Metadata-Version: 2.1
Name: pyevmosaddressconverter
Version: 1.0.1
Summary: Evmos address converter
Home-page: https://github.com/hanchon-live/py-evmos-address-converter
Author: Hanchon
Author-email: guillermo.paoletti@gmail.com
License: MIT
Platform: UNKNOWN
Classifier: License :: OSI Approved :: MIT License
Classifier: Operating System :: OS Independent
Classifier: Programming Language :: Python :: 3
Classifier: Programming Language :: Python :: 3 :: Only
Classifier: Programming Language :: Python :: 3.6
Classifier: Programming Language :: Python :: 3.7
Classifier: Programming Language :: Python :: 3.8
Classifier: Programming Language :: Python :: 3.9
Classifier: Programming Language :: Python :: 3.10
Requires-Python: >=3.6
License-File: LICENSE
